tf_ecosystem-1.0.7.dist-info/METADATA
tf_ecosystem-1.0.7.dist-info/RECORD
tf_ecosystem-1.0.7.dist-info/WHEEL
tf_ecosystem-1.0.7.dist-info/entry_points.txt
tf_ecosystem-1.0.7.dist-info/top_level.txt
tf_ecosystem-1.0.7.dist-info/zip-safe
tfeco/__init__.py
tfeco/composer.py
tfeco/configuration.py
tfeco/configuration_schema.py
tfeco/scripts.py
tfeco/workingdirectory.py
tfeco/tests/__init__.py
tfeco/tests/test_composer.py
