Metadata-Version: 2.1
Name: tf-ecosystem
Version: 1.0.7
Summary: A framework for initialising a terraform environment
Home-page: http://github.com/drewsonne/tf-ecosystem
Author: Drew J. Sonne
Author-email: drew.sonne@gmail.com
License: LGPLv2
Keywords: terraform cli
Platform: UNKNOWN
Classifier: Development Status :: 4 - Beta
Classifier: Environment :: Console
Classifier: License :: OSI Approved :: GNU Lesser General Public License v3 or later (LGPLv3+)
Classifier: Programming Language :: Python :: 3.5
Classifier: Programming Language :: Python :: 3.6
Classifier: Programming Language :: Python :: 3 :: Only
Classifier: Topic :: System
Classifier: Topic :: System :: Systems Administration
Requires-Python: >=3
Requires-Dist: marshmallow
Requires-Dist: click
Requires-Dist: pyaml
Requires-Dist: termcolor
